TODO
dosphinx.py
setup.py
docs/html/genindex.html
docs/html/index.html
docs/html/modindex.html
docs/html/search.html
docs/html/searchindex.json
docs/html/.doctrees/environment.pickle
docs/html/.doctrees/index.doctree
docs/html/.doctrees/modules/controller.doctree
docs/html/.doctrees/modules/model.doctree
docs/html/_sources/index.txt
docs/html/_sources/modules/controller.txt
docs/html/_static/contents.png
docs/html/_static/default.css
docs/html/_static/doctools.js
docs/html/_static/file.png
docs/html/_static/interface.js
docs/html/_static/jquery.js
docs/html/_static/minus.png
docs/html/_static/navigation.png
docs/html/_static/plus.png
docs/html/_static/pygments.css
docs/html/_static/rightsidebar.css
docs/html/_static/searchtools.js
docs/html/_static/sphinxdoc.css
docs/html/_static/stickysidebar.css
docs/html/_static/traditional.css
docs/html/modules/controller.html
docs/html/modules/model.html
docs/source/conf.py
docs/source/index.rst
docs/source/modules/controller.rst
pyfse/__init__.py
pyfse/controller.py
pyfse.egg-info/PKG-INFO
pyfse.egg-info/SOURCES.txt
pyfse.egg-info/dependency_links.txt
pyfse.egg-info/top_level.txt
pyfse.egg-info/zip-safe
tests/import_wrapper.py
tests/tests.py