Metadata-Version: 1.0
Name: pyfse
Version: 0.1.1
Summary:  pyfse: python finite state engine (machine)
